<?xml version="1.0" encoding="utf-8"?>
<search>
  
  
  
  <entry>
    <title>我为什么玩原神</title>
    <link href="/2023/10/22/why_play_genshin/"/>
    <url>/2023/10/22/why_play_genshin/</url>
    
    <content type="html"><![CDATA[<h2 id="摘要"><a href="#摘要" class="headerlink" title="摘要"></a>摘要</h2><p>本论文旨在深入探讨我为什么选择玩原神这款备受瞩目的开放世界冒险游戏。通过分析游戏的多个方面，包括美学、情节、角色、社交因素等，我将阐明原神在我的生活中扮演的独特角色，以及它为何能够吸引数百万玩家。</p><p><img src="/2023/10/22/why_play_genshin/genshin.jpg" alt="Genshin Impact"></p><h2 id="第一部分：美学与沉浸感"><a href="#第一部分：美学与沉浸感" class="headerlink" title="第一部分：美学与沉浸感"></a>第一部分：美学与沉浸感</h2><p>原神以其精美的画面和音乐成为我热衷的游戏之一。提瓦特大陆是一个视觉奇观，每个地方都充满了细致的设计和华丽的景观。从悬崖边的风光到山间的瀑布，每一个场景都令人叹为观止。这种视觉美感让我感受到了一种真实的探险冲动，激励着我去探索更多的地方，寻找隐藏的宝藏。</p><p>游戏的音乐也是令人难以忘怀的。原神的原声音乐为游戏的不同情景增色不少，它们引导了玩家情感，将我们带入游戏的故事情节之中。每个地方的音乐都为其独特的氛围和情感氛围贡献了重要的一部分，这些音乐曲目成为了游戏体验中的一部分，使我感到沉浸其中，仿佛置身于真实的奇幻世界。</p><h2 id="第二部分：故事情节与情感共鸣"><a href="#第二部分：故事情节与情感共鸣" class="headerlink" title="第二部分：故事情节与情感共鸣"></a>第二部分：故事情节与情感共鸣</h2><p>原神的故事情节是游戏中最引人入胜的方面之一。游戏中的角色发展和情节转折都充满了令人着迷的元素。我追随着主人公旅行者的脚步，经历了各种各样的冒险，结识了许多有趣的角色。每个任务都伴随着令人惊喜的情节转折，这让我一直期待着下一个故事发展。</p><p>原神成功地将故事与游戏机制相融合。角色之间的相互作用、他们的背景故事以及游戏中的事件都交织在一起，创造了一个引人入胜的冒险。这让我深陷其中，感受到游戏中的情感共鸣，与角色一同成长。</p><p><img src="/2023/10/22/why_play_genshin/kle-scaled.jpg" alt="Keli"></p><h2 id="第三部分：多样化的角色与战斗机制"><a href="#第三部分：多样化的角色与战斗机制" class="headerlink" title="第三部分：多样化的角色与战斗机制"></a>第三部分：多样化的角色与战斗机制</h2><p>原神的角色和战斗机制为游戏增加了深度和策略性。每个角色都拥有独特的技能和武器，使玩家需要仔细选择角色来应对不同的挑战。元素系统的引入为战斗增添了深度，不同元素之间的相互作用需要玩家灵活运用策略。</p><p>游戏中的每个角色都有各自的故事和背景，这增加了与他们的情感联系。选择特定的角色不仅仅是为了战斗能力，还是为了更深入地了解他们，使他们变得更加有意义。这种深度的角色发展使游戏更加令人着迷，让我感到挑战不断。</p><h2 id="第四部分：探索与社交互动"><a href="#第四部分：探索与社交互动" class="headerlink" title="第四部分：探索与社交互动"></a>第四部分：探索与社交互动</h2><p>原神的开放世界充满了宝藏、谜题和隐藏的秘密，这激发了我探索的欲望。每个地方都似乎有一个故事等待着被揭示，这让我愿意花费数小时来探索提瓦特大陆。游戏中的宝箱和任务将我带到各个角落，不断寻找新的奖励和秘密。</p><p>此外，原神的多人模式为我提供了与朋友一起探索世界和合作战斗的机会。这种社交互动增加了游戏的趣味性，让我感到与朋友之间更紧密的联系。</p><p><img src="/2023/10/22/why_play_genshin/cost.jpg" alt="Cost of playing Genshin"></p><h2 id="结论"><a href="#结论" class="headerlink" title="结论"></a>结论</h2><p>原神作为一款开放世界冒险游戏，融合了精美的美学、深刻的故事情节、多样化的角色和战斗机制，以及令人沉浸的探索与社交互动。通过分析这些方面，我不仅揭示了我为什么玩原神的原因，还认识到这款游戏在游戏界的独特地位，吸引了数百万玩家，成为了一场娱乐的盛宴。原神已经不仅仅是一款游戏，它是一段富有情感和回忆的冒险之旅，持续吸引着我和许多其他玩家。</p>]]></content>
    
    
    <categories>
      
      <category>Genshin</category>
      
      <category>原神</category>
      
      <category>神原</category>
      
    </categories>
    
    
    <tags>
      
      <tag>Genshin</tag>
      
      <tag>原神</tag>
      
    </tags>
    
  </entry>
  
  
  
  
</search>
